Workbook

Sheet Client Database
A1: Client ID | B1: Full Name | C1: National ID | D1: Phone Number | E1: Address | F1: Occupation | G1: Guarantor | H1: Guarantor Phone
A2: C001 | B2: Kwame Asante | C2: GHA-100002 | D2: 024100002 | E2: House No. 12, Mango Street, East Legon, Accra | F2: Trader | G2: Kwame Owusu | H2: 024 512 3481
A3: C002 | B3: Akosua Mensah | C3: GHA-100003 | D3: 024100003 | E3: Plot 45, Liberation Road,Adabraka, Accra | F3: Teacher | G3: Akosua Mensah | H3: 055 781 9246
A4: C003 | B4: Kojo Owusu | C4: GHA-100004 | D4: 024100004 | E4: House No. 8, Anloga Junction, Kumasi | F4: Taxi Driver | G4: Kofi Asante | H4: 020 663 5178
A5: C004 | B5: Ama Serwaa | C5: GHA-100005 | D5: 024100005 | E5: Plot 19, Market Road, Techiman | F5: Farmer | G5: Yaw Boateng | H5: 054 238 6419
A6: C005 | B6: Kofi Boateng | C6: GHA-100006 | D6: 024100006 | E6: House No. 27, Palm Lane, Effiakuma | F6: Seamstress | G6: Abena Ofori | H6: 027 845 1936
A7: C006 | B7: Abena Nyarko | C7: GHA-100007 | D7: 024100007 | E7: Plot 34, Zongo Road, Tamale Central | F7: Civil Servant | G7: Ibrahim Fuseini | H7: 059 416 7582
A8: C007 | B8: Yaw Appiah | C8: GHA-100008 | D8: 024100008 | E8: House No. 15, Lakeside Avenue, Koforidua New Juaben | F8: Nurse | G8: Ama Nyarko | H8: 024 983 2641
A9: C008 | B9: Efua Amoah | C9: GHA-100009 | D9: 024100009 | E9: Plot 52, Independence Street, Ho Bankoe | F9: Hairdresser | G9: Comfort Adjei | H9: 050 741 3859
A10: C009 | B10: Emmanuel Osei | C10: GHA-100010 | D10: 024100010 | E10: House No. 10, Coconut Grove, Cape Coast North | F10: Fisherman | G10: Kojo Essien | H10: 055 692 8147
A11: C010 | B11: Grace Asiedu | C11: GHA-100011 | D11: 024100011 | E11: Plot 7, Hospital Road, Wa Central | F11: Electrician | G11: Samuel Badu | H11: 020 518 4793
A12: C011 | B12: Daniel Mensah | C12: GHA-100012 | D12: 024100012 | E12: House No. 41, Green Hill Street, Bolgatanga East | F12: Shop Attendant | G12: Patricia Akoto | H12: 054 832 7165
... A21: C020 | B21: Janet Ofori | C21: GHA-100021 | D21: 024100021 | E21: Plot 31, Jubilee Avenue, Nalerigu | F21: Pharmacy Assistant | G21: Ruth Azumah | H21: 027 963 5148

Sheet Loan Register
A1: Loan ID | B1: Client ID | C1: Full Name | D1: National ID | E1: Phone Number | F1: Address | G1: Guarantor Name | H1: Guarantor Phone | I1: Loan Date | J1: Loan Amount (₵ | K1: Interest Rate (%) | L1: Loan Term (Months) | M1: Due Date | N1: Expected Monthly Payment | O1: Total Amount to Repay | P1: Amount Repaid | Q1: Outstanding Balance | R1: Due Soon | S1: Status | T1: Remarks
A2: ="LN-"&TEXT(ROW()-1,"0000") -> LN-0001 | B2: C001 | C2: =_xlfn.XLOOKUP(tblLoans[[#This Row],[Client ID]],tblClients[Client ID],tblClients[Full Name],"") -> Kwame Asante | D2: =_xlfn.XLOOKUP(tblLoans[[#This Row],[Client ID]],tblClients[Client ID],tblClients[National ID],"") -> GHA-100002 | E2: =_xlfn.XLOOKUP(tblLoans[[#This Row],[Client ID]],tblClients[Client ID],tblClients[Phone Number],"") -> 024100002 | F2: =_xlfn.XLOOKUP(tblLoans[[#This Row],[Client ID]],tblClients[Client ID],tblClients[Address],"") -> House No. 12, Mango Street, East Legon, Accra | G2: =_xlfn.XLOOKUP(tblLoans[[#This Row],[Client ID]],tblClients[Client ID],tblClients[Guarantor],"") -> Kwame Owusu | H2: =_xlfn.XLOOKUP(tblLoans[[#This Row],[Client ID]],tblClients[Client ID],tblClients[Guarantor Phone],"") -> 024 512 3481 | I2: 45672 | J2: 13500 | K2: 0.24 | L2: 6 | M2: =EDATE(I2,L2) -> 45853 | N2: =O2/L2 -> 2255.4 | O2: =J2*(1+K2/100) -> 13532.4 | P2: =SUMIF(Repayments!C:C,A2,Repayments!E:E) -> 2500 | Q2: =tblLoans[[#This Row],[Total Amount to Repay]]-tblLoans[[#This Row],[Amount Repaid]] -> 11032.4 | R2: =IF(AND(tblLoans[[#This Row],[Outstanding Balance]]>0,tblLoans[[#This Row],[Due Date]]-TODAY()<=14,tblLoans[[#This Row],[Due Date]]>=TODAY()),"Yes","No") -> No | S2: =IF(tblLoans[[#This Row],[Outstanding Balance]]<=0, "Completed", IF(TODAY()>tblLoans[[#This Row],[Due Date]]+90, "Defaulted", IF(TODAY()>tblLoans[[#This Row],[Due Date]], "Overdue", IF(tblLoans[[#This Row],[Due Soon]]="Yes", "Due Soon", "Active")))) -> Defaulted
A3: ="LN-"&TEXT(ROW()-1,"0000") -> LN-0002 | B3: C002 | C3: =_xlfn.XLOOKUP(tblLoans[[#This Row],[Client ID]],tblClients[Client ID],tblClients[Full Name],"") -> Akosua Mensah | D3: =_xlfn.XLOOKUP(tblLoans[[#This Row],[Client ID]],tblClients[Client ID],tblClients[National ID],"") -> GHA-100003 | E3: =_xlfn.XLOOKUP(tblLoans[[#This Row],[Client ID]],tblClients[Client ID],tblClients[Phone Number],"") -> 024100003 | F3: =_xlfn.XLOOKUP(tblLoans[[#This Row],[Client ID]],tblClients[Client ID],tblClients[Address],"") -> Plot 45, Liberation Road,Adabraka, Accra | G3: =_xlfn.XLOOKUP(tblLoans[[#This Row],[Client ID]],tblClients[Client ID],tblClients[Guarantor],"") -> Akosua Mensah | H3: =_xlfn.XLOOKUP(tblLoans[[#This Row],[Client ID]],tblClients[Client ID],tblClients[Guarantor Phone],"") -> 055 781 9246 | I3: 45685 | J3: 5000 | K3: 0.265 | L3: 12 | M3: =EDATE(I3,L3) -> 46050 | N3: =O3/L3 -> 417.77083 | O3: =J3*(1+K3/100) -> 5013.25 | P3: =SUMIF(Repayments!C:C,A3,Repayments!E:E) -> 5100 | Q3: =tblLoans[[#This Row],[Total Amount to Repay]]-tblLoans[[#This Row],[Amount Repaid]] -> -86.75 | R3: =IF(AND(tblLoans[[#This Row],[Outstanding Balance]]>0,tblLoans[[#This Row],[Due Date]]-TODAY()<=14,tblLoans[[#This Row],[Due Date]]>=TODAY()),"Yes","No") -> No | S3: =IF(tblLoans[[#This Row],[Outstanding Balance]]<=0, "Completed", IF(TODAY()>tblLoans[[#This Row],[Due Date]]+90, "Defaulted", IF(TODAY()>tblLoans[[#This Row],[Due Date]], "Overdue", IF(tblLoans[[#This Row],[Due Soon]]="Yes", "Due Soon", "Active")))) -> Completed
A4: ="LN-"&TEXT(ROW()-1,"0000") -> LN-0003 | B4: C003 | C4: =_xlfn.XLOOKUP(tblLoans[[#This Row],[Client ID]],tblClients[Client ID],tblClients[Full Name],"") -> Kojo Owusu | D4: =_xlfn.XLOOKUP(tblLoans[[#This Row],[Client ID]],tblClients[Client ID],tblClients[National ID],"") -> GHA-100004 | E4: =_xlfn.XLOOKUP(tblLoans[[#This Row],[Client ID]],tblClients[Client ID],tblClients[Phone Number],"") -> 024100004 | F4: =_xlfn.XLOOKUP(tblLoans[[#This Row],[Client ID]],tblClients[Client ID],tblClients[Address],"") -> House No. 8, Anloga Junction, Kumasi | G4: =_xlfn.XLOOKUP(tblLoans[[#This Row],[Client ID]],tblClients[Client ID],tblClients[Guarantor],"") -> Kofi Asante | H4: =_xlfn.XLOOKUP(tblLoans[[#This Row],[Client ID]],tblClients[Client ID],tblClients[Guarantor Phone],"") -> 020 663 5178 | I4: 45700 | J4: 8500 | K4: 0.28 | L4: 9 | M4: =EDATE(I4,L4) -> 45973 | N4: =O4/L4 -> 947.08889 | O4: =J4*(1+K4/100) -> 8523.8 | P4: =SUMIF(Repayments!C:C,A4,Repayments!E:E) -> 6000 | Q4: =tblLoans[[#This Row],[Total Amount to Repay]]-tblLoans[[#This Row],[Amount Repaid]] -> 2523.8 | R4: =IF(AND(tblLoans[[#This Row],[Outstanding Balance]]>0,tblLoans[[#This Row],[Due Date]]-TODAY()<=14,tblLoans[[#This Row],[Due Date]]>=TODAY()),"Yes","No") -> No | S4: =IF(tblLoans[[#This Row],[Outstanding Balance]]<=0, "Completed", IF(TODAY()>tblLoans[[#This Row],[Due Date]]+90, "Defaulted", IF(TODAY()>tblLoans[[#This Row],[Due Date]], "Overdue", IF(tblLoans[[#This Row],[Due Soon]]="Yes", "Due Soon", "Active")))) -> Defaulted
A5: ="LN-"&TEXT(ROW()-1,"0000") -> LN-0004 | B5: C004 | C5: =_xlfn.XLOOKUP(tblLoans[[#This Row],[Client ID]],tblClients[Client ID],tblClients[Full Name],"") -> Ama Serwaa | D5: =_xlfn.XLOOKUP(tblLoans[[#This Row],[Client ID]],tblClients[Client ID],tblClients[National ID],"") -> GHA-100005 | E5: =_xlfn.XLOOKUP(tblLoans[[#This Row],[Client ID]],tblClients[Client ID],tblClients[Phone Number],"") -> 024100005 | F5: =_xlfn.XLOOKUP(tblLoans[[#This Row],[Client ID]],tblClients[Client ID],tblClients[Address],"") -> Plot 19, Market Road, Techiman | G5: =_xlfn.XLOOKUP(tblLoans[[#This Row],[Client ID]],tblClients[Client ID],tblClients[Guarantor],"") -> Yaw Boateng | H5: =_xlfn.XLOOKUP(tblLoans[[#This Row],[Client ID]],tblClients[Client ID],tblClients[Guarantor Phone],"") -> 054 238 6419 | I5: 45719 | J5: 12000 | K5: 0.255 | L5: 8 | M5: =EDATE(I5,L5) -> 45964 | N5: =O5/L5 -> 1503.825 | O5: =J5*(1+K5/100) -> 12030.6 | P5: =SUMIF(Repayments!C:C,A5,Repayments!E:E) -> 12000 | Q5: =tblLoans[[#This Row],[Total Amount to Repay]]-tblLoans[[#This Row],[Amount Repaid]] -> 30.6 | R5: =IF(AND(tblLoans[[#This Row],[Outstanding Balance]]>0,tblLoans[[#This Row],[Due Date]]-TODAY()<=14,tblLoans[[#This Row],[Due Date]]>=TODAY()),"Yes","No") -> No | S5: =IF(tblLoans[[#This Row],[Outstanding Balance]]<=0, "Completed", IF(TODAY()>tblLoans[[#This Row],[Due Date]]+90, "Defaulted", IF(TODAY()>tblLoans[[#This Row],[Due Date]], "Overdue", IF(tblLoans[[#This Row],[Due Soon]]="Yes", "Due Soon", "Active")))) -> Defaulted
A6: ="LN-"&TEXT(ROW()-1,"0000") -> LN-0005 | B6: C005 | C6: =_xlfn.XLOOKUP(tblLoans[[#This Row],[Client ID]],tblClients[Client ID],tblClients[Full Name],"") -> Kofi Boateng | D6: =_xlfn.XLOOKUP(tblLoans[[#This Row],[Client ID]],tblClients[Client ID],tblClients[National ID],"") -> GHA-100006 | E6: =_xlfn.XLOOKUP(tblLoans[[#This Row],[Client ID]],tblClients[Client ID],tblClients[Phone Number],"") -> 024100006 | F6: =_xlfn.XLOOKUP(tblLoans[[#This Row],[Client ID]],tblClients[Client ID],tblClients[Address],"") -> House No. 27, Palm Lane, Effiakuma | G6: =_xlfn.XLOOKUP(tblLoans[[#This Row],[Client ID]],tblClients[Client ID],tblClients[Guarantor],"") -> Abena Ofori | H6: =_xlfn.XLOOKUP(tblLoans[[#This Row],[Client ID]],tblClients[Client ID],tblClients[Guarantor Phone],"") -> 027 845 1936 | I6: 45737 | J6: 15000 | K6: 0.3 | L6: 10 | M6: =EDATE(I6,L6) -> 46043 | N6: =O6/L6 -> 1504.5 | O6: =J6*(1+K6/100) -> 15045 | P6: =SUMIF(Repayments!C:C,A6,Repayments!E:E) -> 2600 | Q6: =tblLoans[[#This Row],[Total Amount to Repay]]-tblLoans[[#This Row],[Amount Repaid]] -> 12445 | R6: =IF(AND(tblLoans[[#This Row],[Outstanding Balance]]>0,tblLoans[[#This Row],[Due Date]]-TODAY()<=14,tblLoans[[#This Row],[Due Date]]>=TODAY()),"Yes","No") -> No | S6: =IF(tblLoans[[#This Row],[Outstanding Balance]]<=0, "Completed", IF(TODAY()>tblLoans[[#This Row],[Due Date]]+90, "Defaulted", IF(TODAY()>tblLoans[[#This Row],[Due Date]], "Overdue", IF(tblLoans[[#This Row],[Due Soon]]="Yes", "Due Soon", "Active")))) -> Defaulted
A7: ="LN-"&TEXT(ROW()-1,"0000") -> LN-0006 | B7: C006 | C7: =_xlfn.XLOOKUP(tblLoans[[#This Row],[Client ID]],tblClients[Client ID],tblClients[Full Name],"") -> Abena Nyarko | D7: =_xlfn.XLOOKUP(tblLoans[[#This Row],[Client ID]],tblClients[Client ID],tblClients[National ID],"") -> GHA-100007 | E7: =_xlfn.XLOOKUP(tblLoans[[#This Row],[Client ID]],tblClients[Client ID],tblClients[Phone Number],"") -> 024100007 | F7: =_xlfn.XLOOKUP(tblLoans[[#This Row],[Client ID]],tblClients[Client ID],tblClients[Address],"") -> Plot 34, Zongo Road, Tamale Central | G7: =_xlfn.XLOOKUP(tblLoans[[#This Row],[Client ID]],tblClients[Client ID],tblClients[Guarantor],"") -> Ibrahim Fuseini | H7: =_xlfn.XLOOKUP(tblLoans[[#This Row],[Client ID]],tblClients[Client ID],tblClients[Guarantor Phone],"") -> 059 416 7582 | I7: 45761 | J7: 6500 | K7: 0.225 | L7: 5 | M7: =EDATE(I7,L7) -> 45914 | N7: =O7/L7 -> 1302.925 | O7: =J7*(1+K7/100) -> 6514.625 | P7: =SUMIF(Repayments!C:C,A7,Repayments!E:E) -> 15000 | Q7: =tblLoans[[#This Row],[Total Amount to Repay]]-tblLoans[[#This Row],[Amount Repaid]] -> -8485.375 | R7: =IF(AND(tblLoans[[#This Row],[Outstanding Balance]]>0,tblLoans[[#This Row],[Due Date]]-TODAY()<=14,tblLoans[[#This Row],[Due Date]]>=TODAY()),"Yes","No") -> No | S7: =IF(tblLoans[[#This Row],[Outstanding Balance]]<=0, "Completed", IF(TODAY()>tblLoans[[#This Row],[Due Date]]+90, "Defaulted", IF(TODAY()>tblLoans[[#This Row],[Due Date]], "Overdue", IF(tblLoans[[#This Row],[Due Soon]]="Yes", "Due Soon", "Active")))) -> Completed
A8: ="LN-"&TEXT(ROW()-1,"0000") -> LN-0007 | B8: C007 | C8: =_xlfn.XLOOKUP(tblLoans[[#This Row],[Client ID]],tblClients[Client ID],tblClients[Full Name],"") -> Yaw Appiah | D8: =_xlfn.XLOOKUP(tblLoans[[#This Row],[Client ID]],tblClients[Client ID],tblClients[National ID],"") -> GHA-100008 | E8: =_xlfn.XLOOKUP(tblLoans[[#This Row],[Client ID]],tblClients[Client ID],tblClients[Phone Number],"") -> 024100008 | F8: =_xlfn.XLOOKUP(tblLoans[[#This Row],[Client ID]],tblClients[Client ID],tblClients[Address],"") -> House No. 15, Lakeside Avenue, Koforidua New Juaben | G8: =_xlfn.XLOOKUP(tblLoans[[#This Row],[Client ID]],tblClients[Client ID],tblClients[Guarantor],"") -> Ama Nyarko | H8: =_xlfn.XLOOKUP(tblLoans[[#This Row],[Client ID]],tblClients[Client ID],tblClients[Guarantor Phone],"") -> 024 983 2641 | I8: 45786 | J8: 20000 | K8: 0.27 | L8: 3 | M8: =EDATE(I8,L8) -> 45878 | N8: =O8/L8 -> 6684.6667 | O8: =J8*(1+K8/100) -> 20054 | P8: =SUMIF(Repayments!C:C,A8,Repayments!E:E) -> 7500 | Q8: =tblLoans[[#This Row],[Total Amount to Repay]]-tblLoans[[#This Row],[Amount Repaid]] -> 12554 | R8: =IF(AND(tblLoans[[#This Row],[Outstanding Balance]]>0,tblLoans[[#This Row],[Due Date]]-TODAY()<=14,tblLoans[[#This Row],[Due Date]]>=TODAY()),"Yes","No") -> No | S8: =IF(tblLoans[[#This Row],[Outstanding Balance]]<=0, "Completed", IF(TODAY()>tblLoans[[#This Row],[Due Date]]+90, "Defaulted", IF(TODAY()>tblLoans[[#This Row],[Due Date]], "Overdue", IF(tblLoans[[#This Row],[Due Soon]]="Yes", "Due Soon", "Active")))) -> Defaulted
A9: ="LN-"&TEXT(ROW()-1,"0000") -> LN-0008 | B9: C008 | C9: =_xlfn.XLOOKUP(tblLoans[[#This Row],[Client ID]],tblClients[Client ID],tblClients[Full Name],"") -> Efua Amoah | D9: =_xlfn.XLOOKUP(tblLoans[[#This Row],[Client ID]],tblClients[Client ID],tblClients[National ID],"") -> GHA-100009 | E9: =_xlfn.XLOOKUP(tblLoans[[#This Row],[Client ID]],tblClients[Client ID],tblClients[Phone Number],"") -> 024100009 | F9: =_xlfn.XLOOKUP(tblLoans[[#This Row],[Client ID]],tblClients[Client ID],tblClients[Address],"") -> Plot 52, Independence Street, Ho Bankoe | G9: =_xlfn.XLOOKUP(tblLoans[[#This Row],[Client ID]],tblClients[Client ID],tblClients[Guarantor],"") -> Comfort Adjei | H9: =_xlfn.XLOOKUP(tblLoans[[#This Row],[Client ID]],tblClients[Client ID],tblClients[Guarantor Phone],"") -> 050 741 3859 | I9: 45804 | J9: 10000 | K9: 0.315 | L9: 2 | M9: =EDATE(I9,L9) -> 45865 | N9: =O9/L9 -> 5015.75 | O9: =J9*(1+K9/100) -> 10031.5 | P9: =SUMIF(Repayments!C:C,A9,Repayments!E:E) -> 1350 | Q9: =tblLoans[[#This Row],[Total Amount to Repay]]-tblLoans[[#This Row],[Amount Repaid]] -> 8681.5 | R9: =IF(AND(tblLoans[[#This Row],[Outstanding Balance]]>0,tblLoans[[#This Row],[Due Date]]-TODAY()<=14,tblLoans[[#This Row],[Due Date]]>=TODAY()),"Yes","No") -> No | S9: =IF(tblLoans[[#This Row],[Outstanding Balance]]<=0, "Completed", IF(TODAY()>tblLoans[[#This Row],[Due Date]]+90, "Defaulted", IF(TODAY()>tblLoans[[#This Row],[Due Date]], "Overdue", IF(tblLoans[[#This Row],[Due Soon]]="Yes", "Due Soon", "Active")))) -> Defaulted
A10: ="LN-"&TEXT(ROW()-1,"0000") -> LN-0009 | B10: C009 | C10: =_xlfn.XLOOKUP(tblLoans[[#This Row],[Client ID]],tblClients[Client ID],tblClients[Full Name],"") -> Emmanuel Osei | D10: =_xlfn.XLOOKUP(tblLoans[[#This Row],[Client ID]],tblClients[Client ID],tblClients[National ID],"") -> GHA-100010 | E10: =_xlfn.XLOOKUP(tblLoans[[#This Row],[Client ID]],tblClients[Client ID],tblClients[Phone Number],"") -> 024100010 | F10: =_xlfn.XLOOKUP(tblLoans[[#This Row],[Client ID]],tblClients[Client ID],tblClients[Address],"") -> House No. 10, Coconut Grove, Cape Coast North | G10: =_xlfn.XLOOKUP(tblLoans[[#This Row],[Client ID]],tblClients[Client ID],tblClients[Guarantor],"") -> Kojo Essien | H10: =_xlfn.XLOOKUP(tblLoans[[#This Row],[Client ID]],tblClients[Client ID],tblClients[Guarantor Phone],"") -> 055 692 8147 | I10: 45826 | J10: 4500 | K10: 0.29 | L10: 1 | M10: =EDATE(I10,L10) -> 45856 | N10: =O10/L10 -> 4513.05 | O10: =J10*(1+K10/100) -> 4513.05 | P10: =SUMIF(Repayments!C:C,A10,Repayments!E:E) -> 3900 | Q10: =tblLoans[[#This Row],[Total Amount to Repay]]-tblLoans[[#This Row],[Amount Repaid]] -> 613.05 | R10: =IF(AND(tblLoans[[#This Row],[Outstanding Balance]]>0,tblLoans[[#This Row],[Due Date]]-TODAY()<=14,tblLoans[[#This Row],[Due Date]]>=TODAY()),"Yes","No") -> No | S10: =IF(tblLoans[[#This Row],[Outstanding Balance]]<=0, "Completed", IF(TODAY()>tblLoans[[#This Row],[Due Date]]+90, "Defaulted", IF(TODAY()>tblLoans[[#This Row],[Due Date]], "Overdue", IF(tblLoans[[#This Row],[Due Soon]]="Yes", "Due Soon", "Active")))) -> Defaulted
A11: ="LN-"&TEXT(ROW()-1,"0000") -> LN-0010 | B11: C010 | C11: =_xlfn.XLOOKUP(tblLoans[[#This Row],[Client ID]],tblClients[Client ID],tblClients[Full Name],"") -> Grace Asiedu | D11: =_xlfn.XLOOKUP(tblLoans[[#This Row],[Client ID]],tblClients[Client ID],tblClients[National ID],"") -> GHA-100011 | E11: =_xlfn.XLOOKUP(tblLoans[[#This Row],[Client ID]],tblClients[Client ID],tblClients[Phone Number],"") -> 024100011 | F11: =_xlfn.XLOOKUP(tblLoans[[#This Row],[Client ID]],tblClients[Client ID],tblClients[Address],"") -> Plot 7, Hospital Road, Wa Central | G11: =_xlfn.XLOOKUP(tblLoans[[#This Row],[Client ID]],tblClients[Client ID],tblClients[Guarantor],"") -> Samuel Badu | H11: =_xlfn.XLOOKUP(tblLoans[[#This Row],[Client ID]],tblClients[Client ID],tblClients[Guarantor Phone],"") -> 020 518 4793 | I11: 45849 | J11: 7800 | K11: 0.23 | L11: 4 | M11: =EDATE(I11,L11) -> 45972 | N11: =O11/L11 -> 1954.485 | O11: =J11*(1+K11/100) -> 7817.94 | P11: =SUMIF(Repayments!C:C,A11,Repayments!E:E) -> 9000 | Q11: =tblLoans[[#This Row],[Total Amount to Repay]]-tblLoans[[#This Row],[Amount Repaid]] -> -1182.06 | R11: =IF(AND(tblLoans[[#This Row],[Outstanding Balance]]>0,tblLoans[[#This Row],[Due Date]]-TODAY()<=14,tblLoans[[#This Row],[Due Date]]>=TODAY()),"Yes","No") -> No | S11: =IF(tblLoans[[#This Row],[Outstanding Balance]]<=0, "Completed", IF(TODAY()>tblLoans[[#This Row],[Due Date]]+90, "Defaulted", IF(TODAY()>tblLoans[[#This Row],[Due Date]], "Overdue", IF(tblLoans[[#This Row],[Due Soon]]="Yes", "Due Soon", "Active")))) -> Completed
A12: ="LN-"&TEXT(ROW()-1,"0000") -> LN-0011 | B12: C011 | C12: =_xlfn.XLOOKUP(tblLoans[[#This Row],[Client ID]],tblClients[Client ID],tblClients[Full Name],"") -> Daniel Mensah | D12: =_xlfn.XLOOKUP(tblLoans[[#This Row],[Client ID]],tblClients[Client ID],tblClients[National ID],"") -> GHA-100012 | E12: =_xlfn.XLOOKUP(tblLoans[[#This Row],[Client ID]],tblClients[Client ID],tblClients[Phone Number],"") -> 024100012 | F12: =_xlfn.XLOOKUP(tblLoans[[#This Row],[Client ID]],tblClients[Client ID],tblClients[Address],"") -> House No. 41, Green Hill Street, Bolgatanga East | G12: =_xlfn.XLOOKUP(tblLoans[[#This Row],[Client ID]],tblClients[Client ID],tblClients[Guarantor],"") -> Patricia Akoto | H12: =_xlfn.XLOOKUP(tblLoans[[#This Row],[Client ID]],tblClients[Client ID],tblClients[Guarantor Phone],"") -> 054 832 7165 | I12: 45894 | J12: 18000 | K12: 0.32 | L12: 7 | M12: =EDATE(I12,L12) -> 46106 | N12: =O12/L12 -> 2579.6571 | O12: =J12*(1+K12/100) -> 18057.6 | P12: =SUMIF(Repayments!C:C,A12,Repayments!E:E) -> 1750 | Q12: =tblLoans[[#This Row],[Total Amount to Repay]]-tblLoans[[#This Row],[Amount Repaid]] -> 16307.6 | R12: =IF(AND(tblLoans[[#This Row],[Outstanding Balance]]>0,tblLoans[[#This Row],[Due Date]]-TODAY()<=14,tblLoans[[#This Row],[Due Date]]>=TODAY()),"Yes","No") -> No | S12: =IF(tblLoans[[#This Row],[Outstanding Balance]]<=0, "Completed", IF(TODAY()>tblLoans[[#This Row],[Due Date]]+90, "Defaulted", IF(TODAY()>tblLoans[[#This Row],[Due Date]], "Overdue", IF(tblLoans[[#This Row],[Due Soon]]="Yes", "Due Soon", "Active")))) -> Defaulted
A13: ="LN-"&TEXT(ROW()-1,"0000") -> LN-0012 | B13: C012 | C13: =_xlfn.XLOOKUP(tblLoans[[#This Row],[Client ID]],tblClients[Client ID],tblClients[Full Name],"") -> Patricia Baah | D13: =_xlfn.XLOOKUP(tblLoans[[#This Row],[Client ID]],tblClients[Client ID],tblClients[National ID],"") -> GHA-100013 | E13: =_xlfn.XLOOKUP(tblLoans[[#This Row],[Client ID]],tblClients[Client ID],tblClients[Phone Number],"") -> 024100013 | F13: =_xlfn.XLOOKUP(tblLoans[[#This Row],[Client ID]],tblClients[Client ID],tblClients[Address],"") -> Plot 29, Community 11 Road, Tema Community 11 | G13: =_xlfn.XLOOKUP(tblLoans[[#This Row],[Client ID]],tblClients[Client ID],tblClients[Guarantor],"") -> Josephine Quaye | H13: =_xlfn.XLOOKUP(tblLoans[[#This Row],[Client ID]],tblClients[Client ID],tblClients[Guarantor Phone],"") -> 027 604 9281 | I13: 45916 | J13: 3500 | K13: 0.22 | L13: 11 | M13: =EDATE(I13,L13) -> 46250 | N13: =O13/L13 -> 318.88182 | O13: =J13*(1+K13/100) -> 3507.7 | P13: =SUMIF(Repayments!C:C,A13,Repayments!E:E) -> 20000 | Q13: =tblLoans[[#This Row],[Total Amount to Repay]]-tblLoans[[#This Row],[Amount Repaid]] -> -16492.3 | R13: =IF(AND(tblLoans[[#This Row],[Outstanding Balance]]>0,tblLoans[[#This Row],[Due Date]]-TODAY()<=14,tblLoans[[#This Row],[Due Date]]>=TODAY()),"Yes","No") -> No | S13: =IF(tblLoans[[#This Row],[Outstanding Balance]]<=0, "Completed", IF(TODAY()>tblLoans[[#This Row],[Due Date]]+90, "Defaulted", IF(TODAY()>tblLoans[[#This Row],[Due Date]], "Overdue", IF(tblLoans[[#This Row],[Due Soon]]="Yes", "Due Soon", "Active")))) -> Completed
... A21: ="LN-"&TEXT(ROW()-1,"0000") -> LN-0020 | B21: C020 | C21: =_xlfn.XLOOKUP(tblLoans[[#This Row],[Client ID]],tblClients[Client ID],tblClients[Full Name],"") -> Janet Ofori | D21: =_xlfn.XLOOKUP(tblLoans[[#This Row],[Client ID]],tblClients[Client ID],tblClients[National ID],"") -> GHA-100021 | E21: =_xlfn.XLOOKUP(tblLoans[[#This Row],[Client ID]],tblClients[Client ID],tblClients[Phone Number],"") -> 024100021 | F21: =_xlfn.XLOOKUP(tblLoans[[#This Row],[Client ID]],tblClients[Client ID],tblClients[Address],"") -> Plot 31, Jubilee Avenue, Nalerigu | G21: =_xlfn.XLOOKUP(tblLoans[[#This Row],[Client ID]],tblClients[Client ID],tblClients[Guarantor],"") -> Ruth Azumah | H21: =_xlfn.XLOOKUP(tblLoans[[#This Row],[Client ID]],tblClients[Client ID],tblClients[Guarantor Phone],"") -> 027 963 5148 | I21: 46171 | J21: 16000 | K21: 0.295 | L21: 8 | M21: =EDATE(I21,L21) -> 46416 | N21: =O21/L21 -> 2005.9 | O21: =J21*(1+K21/100) -> 16047.2 | P21: =SUMIF(Repayments!C:C,A21,Repayments!E:E) -> 5400 | Q21: =tblLoans[[#This Row],[Total Amount to Repay]]-tblLoans[[#This Row],[Amount Repaid]] -> 10647.2 | R21: =IF(AND(tblLoans[[#This Row],[Outstanding Balance]]>0,tblLoans[[#This Row],[Due Date]]-TODAY()<=14,tblLoans[[#This Row],[Due Date]]>=TODAY()),"Yes","No") -> No | S21: =IF(tblLoans[[#This Row],[Outstanding Balance]]<=0, "Completed", IF(TODAY()>tblLoans[[#This Row],[Due Date]]+90, "Defaulted", IF(TODAY()>tblLoans[[#This Row],[Due Date]], "Overdue", IF(tblLoans[[#This Row],[Due Soon]]="Yes", "Due Soon", "Active")))) -> Active

Sheet Repayments
A1: Receipt No | B1: Date Paid | C1: Loan ID | D1: Client ID | E1: Amount Paid | F1: Payment Method | G1: Received By | H1: Remarks
A2: ="RCT"&TEXT(ROW()-1,"0000") -> RCT0001 | B2: 46067 | C2: ="LN-"&TEXT(ROW()-1,"0000") -> LN-0001 | D2: =_xlfn.XLOOKUP(tblRepayments[[#This Row],[Loan ID]],tblLoans[Loan ID],tblLoans[Client ID],"") -> C001 | E2: 2500 | F2: Mobile Money | G2: Lender (Melody Esinam Agyeman)
A3: ="RCT"&TEXT(ROW()-1,"0000") -> RCT0002 | B3: 46072 | C3: ="LN-"&TEXT(ROW()-1,"0000") -> LN-0002 | D3: =_xlfn.XLOOKUP(tblRepayments[[#This Row],[Loan ID]],tblLoans[Loan ID],tblLoans[Client ID],"") -> C002 | E3: 5100 | F3: Bank Transfer | G3: Lender (Melody Esinam Agyeman)
A4: ="RCT"&TEXT(ROW()-1,"0000") -> RCT0003 | B4: 46077 | C4: ="LN-"&TEXT(ROW()-1,"0000") -> LN-0003 | D4: =_xlfn.XLOOKUP(tblRepayments[[#This Row],[Loan ID]],tblLoans[Loan ID],tblLoans[Client ID],"") -> C003 | E4: 6000 | F4: Cash | G4: Lender (Melody Esinam Agyeman)
A5: ="RCT"&TEXT(ROW()-1,"0000") -> RCT0004 | B5: 46082 | C5: ="LN-"&TEXT(ROW()-1,"0000") -> LN-0004 | D5: =_xlfn.XLOOKUP(tblRepayments[[#This Row],[Loan ID]],tblLoans[Loan ID],tblLoans[Client ID],"") -> C004 | E5: 12000 | F5: Mobile Money | G5: Lender (Melody Esinam Agyeman)
A6: ="RCT"&TEXT(ROW()-1,"0000") -> RCT0005 | B6: 46087 | C6: ="LN-"&TEXT(ROW()-1,"0000") -> LN-0005 | D6: =_xlfn.XLOOKUP(tblRepayments[[#This Row],[Loan ID]],tblLoans[Loan ID],tblLoans[Client ID],"") -> C005 | E6: 2600 | F6: Mobile Money | G6: Lender (Melody Esinam Agyeman)
A7: ="RCT"&TEXT(ROW()-1,"0000") -> RCT0006 | B7: 46092 | C7: ="LN-"&TEXT(ROW()-1,"0000") -> LN-0006 | D7: =_xlfn.XLOOKUP(tblRepayments[[#This Row],[Loan ID]],tblLoans[Loan ID],tblLoans[Client ID],"") -> C006 | E7: 15000 | F7: Mobile Money | G7: Lender (Melody Esinam Agyeman)
A8: ="RCT"&TEXT(ROW()-1,"0000") -> RCT0007 | B8: 46097 | C8: ="LN-"&TEXT(ROW()-1,"0000") -> LN-0007 | D8: =_xlfn.XLOOKUP(tblRepayments[[#This Row],[Loan ID]],tblLoans[Loan ID],tblLoans[Client ID],"") -> C007 | E8: 7500 | F8: Mobile Money | G8: Lender (Melody Esinam Agyeman)
A9: ="RCT"&TEXT(ROW()-1,"0000") -> RCT0008 | B9: 46102 | C9: ="LN-"&TEXT(ROW()-1,"0000") -> LN-0008 | D9: =_xlfn.XLOOKUP(tblRepayments[[#This Row],[Loan ID]],tblLoans[Loan ID],tblLoans[Client ID],"") -> C008 | E9: 1350 | F9: Mobile Money | G9: Lender (Melody Esinam Agyeman)
A10: ="RCT"&TEXT(ROW()-1,"0000") -> RCT0009 | B10: 46107 | C10: ="LN-"&TEXT(ROW()-1,"0000") -> LN-0009 | D10: =_xlfn.XLOOKUP(tblRepayments[[#This Row],[Loan ID]],tblLoans[Loan ID],tblLoans[Client ID],"") -> C009 | E10: 3900 | F10: Bank Transfer | G10: Lender (Melody Esinam Agyeman)
A11: ="RCT"&TEXT(ROW()-1,"0000") -> RCT0010 | B11: 46112 | C11: ="LN-"&TEXT(ROW()-1,"0000") -> LN-0010 | D11: =_xlfn.XLOOKUP(tblRepayments[[#This Row],[Loan ID]],tblLoans[Loan ID],tblLoans[Client ID],"") -> C010 | E11: 9000 | F11: Mobile Money | G11: Lender (Melody Esinam Agyeman)
A12: ="RCT"&TEXT(ROW()-1,"0000") -> RCT0011 | B12: 46117 | C12: ="LN-"&TEXT(ROW()-1,"0000") -> LN-0011 | D12: =_xlfn.XLOOKUP(tblRepayments[[#This Row],[Loan ID]],tblLoans[Loan ID],tblLoans[Client ID],"") -> C011 | E12: 1750 | F12: Cash | G12: Lender (Melody Esinam Agyeman)
A13: ="RCT"&TEXT(ROW()-1,"0000") -> RCT0012 | B13: 46122 | C13: ="LN-"&TEXT(ROW()-1,"0000") -> LN-0012 | D13: =_xlfn.XLOOKUP(tblRepayments[[#This Row],[Loan ID]],tblLoans[Loan ID],tblLoans[Client ID],"") -> C012 | E13: 20000 | F13: Mobile Money | G13: Lender (Melody Esinam Agyeman)
... A21: ="RCT"&TEXT(ROW()-1,"0000") -> RCT0020 | B21: 46162 | C21: ="LN-"&TEXT(ROW()-1,"0000") -> LN-0020 | D21: =_xlfn.XLOOKUP(tblRepayments[[#This Row],[Loan ID]],tblLoans[Loan ID],tblLoans[Client ID],"") -> C020 | E21: 5400 | F21: Mobile Money | G21: Lender (Melody Esinam Agyeman)

Sheet Dashboard
A1: Lending Dashboard
A2: KPI | B2: VALUE
A3: Total Loans Issued | B3: =COUNTA(tblLoans[Loan ID]) -> 20
A4: Total Amount Disbursed | B4: =SUM('Loan Register'!J:J) -> 258100
A5: Total Amount Collected | B5: =SUM(tblRepayments[Amount Paid]) -> 159070
A6: Outstanding Portfolio | B6: =SUM(tblLoans[Outstanding Balance]) -> 99737.59
A7: Active Loans | B7: =COUNTIF(tblLoans[Status],"Active") -> 3
A8: Overdue Loans | B8: =COUNTIF(tblLoans[Status],"Overdue") -> 1
A9: Completed Loans | B9: =COUNTIF(tblLoans[Status],"Completed") -> 6
A10: Loans Due Soon | B10: =COUNTIF(tblLoans[Due Soon],"Yes") -> 0
A12: Active | B12: =COUNTIF('Loan Register'!S:S,A12) -> 3
A13: Due Soon | B13: =COUNTIF('Loan Register'!S:S,A13) -> 0
A14: Overdue | B14: =COUNTIF('Loan Register'!S:S,A14) -> 1
A15: Completed | B15: =COUNTIF('Loan Register'!S:S,A15) -> 6

Sheet  Monthly Collections
A3: Row Labels | B3: Sum of Amount Paid
A4: 46067 | B4: 2500
A5: 46072 | B5: 5100
A6: 46077 | B6: 6000
A7: 46082 | B7: 12000
A8: 46087 | B8: 2600
A9: 46092 | B9: 15000
A10: 46097 | B10: 7500
A11: 46102 | B11: 1350
A12: 46107 | B12: 3900
A13: 46112 | B13: 9000
A14: 46117 | B14: 1750
A15: 46122 | B15: 20000
... A23: 46162 | B23: 5400
A24: Grand Total | B24: 159070

Sheet Loan Status Distribution 
A3: Row Labels | B3: Count of Loan ID
A4: Active | B4: 3
A5: Completed | B5: 6
A6: Defaulted | B6: 9
A7: Overdue | B7: 2
A8: Grand Total | B8: 20

Sheet Loans Due Soon
A3: Row Labels | B3: Count of Loan ID
A4: No | B4: 20
A5: Grand Total | B5: 20
